MANIFEST.in
requirements.txt
setup.py
clover/__init__.py
clover/builder.py
clover/command.py
clover/main.py
clover/service.py
clover/solver.py
clover/sourcefile.py
clover.egg-info/PKG-INFO
clover.egg-info/SOURCES.txt
clover.egg-info/dependency_links.txt
clover.egg-info/entry_points.txt
clover.egg-info/not-zip-safe
clover.egg-info/requires.txt
clover.egg-info/top_level.txt
clover/closure/__init__.py
clover/closure/client.py
clover/closure/compiler.py
clover/closure/compiler_test.py
clover/closure/inputmanifest.py
clover/closure/jpypeclient.py
clover/closure/messageextractor.py
clover/closure/outputmanifest.py
clover/closure/soycompiler.py
clover/commands/__init__.py
clover/commands/build.py
clover/commands/convertpo.py
clover/commands/externs.py
clover/commands/messages.py
clover/commands/serve.py
clover/commands/test.py
clover/config/__init__.py
clover/config/baseconfig.py
clover/config/cloverconfig.py
clover/config/dictconfig.py
clover/config/markedloader.py
clover/config/multiconfig.py
clover/config/options.py
clover/config/yamlconfig.py
clover/jars/clover.jar
clover/javascript/externs/deprecated.js
clover/javascript/externs/es3.js
clover/javascript/externs/es5.js
clover/javascript/externs/fileapi.js
clover/javascript/externs/flash.js
clover/javascript/externs/gears_symbols.js
clover/javascript/externs/gears_types.js
clover/javascript/externs/gecko_css.js
clover/javascript/externs/gecko_dom.js
clover/javascript/externs/gecko_event.js
clover/javascript/externs/gecko_xml.js
clover/javascript/externs/google.js
clover/javascript/externs/html5.js
clover/javascript/externs/ie_css.js
clover/javascript/externs/ie_dom.js
clover/javascript/externs/ie_event.js
clover/javascript/externs/ie_vml.js
clover/javascript/externs/iphone.js
clover/javascript/externs/w3c_anim_timing.js
clover/javascript/externs/w3c_css.js
clover/javascript/externs/w3c_css3d.js
clover/javascript/externs/w3c_device_sensor_event.js
clover/javascript/externs/w3c_dom1.js
clover/javascript/externs/w3c_dom2.js
clover/javascript/externs/w3c_dom3.js
clover/javascript/externs/w3c_elementtraversal.js
clover/javascript/externs/w3c_event.js
clover/javascript/externs/w3c_event3.js
