Metadata-Version: 1.0
Name: clover
Version: 0.2.1
Summary: 
